setup.cfg
setup.py
valid_pymail/__init__.py
valid_pymail/validator.py
valid_pymail.egg-info/PKG-INFO
valid_pymail.egg-info/SOURCES.txt
valid_pymail.egg-info/dependency_links.txt
valid_pymail.egg-info/top_level.txt