Metadata-Version: 1.1
Name: valid-pymail
Version: 0.1.1
Summary: A wrapper for the Mailgun email validator API
Home-page: https://github.com/knockrentals/valid_pymail
Author: Michael Malocha
Author-email: mmalocha13@gmail.com
License: BSD
Download-URL: https://github.com/knockrentals/valid_pymail/tarball/0.1
Keywords: mailgun email validator API wrapper
Platform: UNKNOWN
Classifier: Development Status :: 3 - Alpha
Classifier: Topic :: Utilities
Classifier: License :: OSI Approved :: BSD License
